gelfguru/__init__.py
gelfguru-0.1.3.dist-info/LICENSE
gelfguru-0.1.3.dist-info/WHEEL
gelfguru-0.1.3.dist-info/METADATA
gelfguru-0.1.3.dist-info/RECORD
