Metadata-Version: 2.1
Name: gelfguru
Version: 0.1.3
Summary: Loguru extension for log in GELF payload format.
Home-page: https://github.com/augustoliks/loguru-gelf-extension/tree/develop
License: Apache-2.0
Author: Carlos Neto
Author-email: carlos.santos110@fatec.sp.gov.br
Requires-Python: >=3.7,<4.0
Classifier: License :: OSI Approved :: Apache Software License
Classifier: Programming Language :: Python :: 3
Classifier: Programming Language :: Python :: 3.7
Classifier: Programming Language :: Python :: 3.8
Classifier: Topic :: Internet :: Log Analysis
Classifier: Topic :: Software Development :: Libraries :: Python Modules
Requires-Dist: loguru (>=0.5.1,<0.6.0)
Project-URL: Documentation, https://github.com/augustoliks/loguru-gelf-extension/blob/develop/README.md
